spark_validation/__init__.py
spark_validation/app.py
spark_validation/version.py
spark_validation/common/__init__.py
spark_validation/common/config.py
spark_validation/common/constants.py
spark_validation/common/general_validator.py
spark_validation/common/validation_results.py
spark_validation/dataframe_validation/__init__.py
spark_validation/dataframe_validation/dataframe_validator.py
spark_validation/dataframe_validation/file_system_validator.py
spark_validation/dataframe_validation/hive_validator.py
owl_sanitizer_data_quality-0.5.dist-info/METADATA
owl_sanitizer_data_quality-0.5.dist-info/WHEEL
owl_sanitizer_data_quality-0.5.dist-info/top_level.txt
owl_sanitizer_data_quality-0.5.dist-info/RECORD
