Metadata-Version: 2.1
Name: owl-sanitizer-data-quality
Version: 0.5
Summary: Data Quality framework for Pyspark jobs
Home-page: https://github.com/ronald-smith-angel/owl-data-sanitizer.git
Author: Ronald Angel
Author-email: ronaldsmithangel@gmail.com
License: MIT
Platform: UNKNOWN
Requires-Dist: dataclasses (==0.6)
Requires-Dist: pyspark (==2.4.5)
Requires-Dist: Flask (==1.1.2)
Requires-Dist: requests (==2.23.0)
Requires-Dist: numpy (==1.18.3)
Requires-Dist: pandas (==1.0.1)
Requires-Dist: pivottablejs (==0.9.0)
Requires-Dist: ipython (==7.13.0)
